{
  "id": "Barrons_Barron_s_13,_April_2026_pt426",
  "title": "Barron_s 13, April 2026 - Part 426",
  "source": "Barrons",
  "difficulty": "Advanced",
  "date": "2026-06-13T18:35:51.986Z",
  "coverImg": "https://images.unsplash.com/photo-1585829365295-ab7cd400c167?w=500&q=80",
  "content": "DirexSCBl3                                                                                                                  TNA                                   .5  51.36     ...    .02                                                                                                                                    InvscShTermTrea                                                                                                           TBLL                           4.6                     105.67                              +0.06                                      .296 iShMSCIEAFEGrw      EFG   ...                                                                                                                                                              118.46                               +5.63     ...\n\nGrShr2xLgNOW                                                                                                             NOWL                                  ...   3.69     ...     ...                                                                                                                                                                                                                                                                                                                                                                                                                                                                                                                                                                                                                                                                                                                                                                               JanusHendersonAAA                                                                                                        JAAA                             5.1                   50.50                                                    ...               .2456                                              TemaSpaceInnova                                                                                                           NASA                                  ...  28.51  +1.31     ...\n\nDirexScBr3             TZA  3.6  6.00     ...                                                                                                                                                                                                                                       .0709                                              InvscSrLoan                                                                                                                 BKLN                           7.0                     20.49                                +0.01  .1155 iShMSCIChile           ECH   ...                                                                                                                                                                  42.45                                +2.41     ...\n\nGrShr2xLgNBISDly                                                                                                          NBIL                                   ...  19.73     ...     ...                                                                                                                                                                                                                                                                                                                                                                                                                                                                                                                                                                                                                                                                                                                                                                              iShUSThematicRot                                                                                                          THRO                                  .2               38.30                                 +1.60  .0318                                                                             SSUtilsSel              XLU  2.5                                                                                                                                                                    46.96                               +0.62                               .3099 DirexSemiBl3                                                                                                               SOXL                                   ...  76.39     ...     ...                                                                                                                                     InvscS&PIntlDev                                                                                                            IDMO                             1.9                    59.20                                +3.32  .2657 iShIntlAggBd                                                                                                                IAGG                                   ...               49.92                               +0.09                                                    ..."
}