{
  "id": "Barrons_Barron_s_18_May_2026_pt224",
  "title": "Barron_s 18 May 2026 - Part 224",
  "source": "Barrons",
  "difficulty": "Intermediate",
  "date": "2026-06-13T18:35:55.300Z",
  "coverImg": "https://images.unsplash.com/photo-1585829365295-ab7cd400c167?w=500&q=80",
  "content": "81.09 50.24 CarrierGlobal                                                                                                                                                  CARR                             1.5  42 64.67                                                                         –2.16                                .24 10.80   4.15 Volaris                                                                                                                                                          VLRS                                   ...  dd   6.53 –1.15   ...                                                                                                                                                52.66  27.15 DuPont           DD   1.6  dd  49.31                                                                                                                                                                                                                                                                   –0.45                                .20                                     155.19                                125.71                                ExtraSpaceSt    EXR  4.7   31                                                                                                                                                           136.90                                –6.40                           1.62 em 37.02   0.78                                                                GenerationEssen                                                                                TGE   ...  dd    .98                                                                                                            +0.01                                       ...\n\n52.10 39.88 CarriageSvcs     CSV  1.0  16 43.22                                                                                                                                                                                                                                                           –2.24                       .1125 34.94  11.23 Constellium                                                                                                                                                     CSTM                                   ...  10  31.91                                                                      –1.97                                         ...                              134.49                               113.39                                DukeEnergy      DUK  3.5  19                                                                                                                                                            120.95                                –3.22                        1.065                                                 18.73   7.57 Expro                                                                                                                                                          XPRO                                   ...  50  15.85                                                                     +0.48                                       ...\n\n87.62 46.82 GeneralMotors   GM    .9  30 74.86                                                                                                                                                                                                                                                           –3.94                                  .18                                                                                      Wea 475.69                               219.58                                CarpenterTech   CRS   .2  43                                                                                                                                                           408.93                                –18.92                               .20 196.91                                126.45                               ConstBrands A   STZ  2.9  15                                                                                                                                                          142.35                                –5.86                           1.03                                         156.32                                 66.24 Ducommun       DCO   ...  dd                                                                                                                                                                                             143.75                                +6.52                                       ...                              167.19                                109.90                               ExpeditorsIntl                                                                                   EXPD                             1.0  25                                         155.45                                –1.24                                  .81 55.35  32.91 GeneralMills     GIS   7.4   8  32.99                                                                                                                                                                                                                                                             –1.69                                  .61 34.03  21.62 Carnival          CCL  2.4   11 24.64                                                                                                                                                                                                                                                                 –1.74                                   .15 116.23                                  94.96 ConEd            ED   3.4  18                                                                                                                                                                                                  105.36                                –0.95                       .8875                                               31.50  12.58 DreamFinders    DFH   ...   8  13.10                                                                                                                                                                                                                                                            –1.22                                         ...                                  43.18  21.29 ExcelerateEner   EE     .9  29  35.71                                                                                                                                                                                                                                                            +1.82                               .08 ck, 369.70                               268.10                               GeneralDynamics                                                                                GD   1.9  21                                                                         334.50                                –12.03                          1.59 71.99 30.26 CarMax          KMX   ...  23  36.93                                                                                                                                                                                                                                                                –3.41                                         ..."
}