{
  "id": "Barrons_Barron_s_11,_May_2026_pt198",
  "title": "Barron_s  11, May 2026 - Part 198",
  "source": "Barrons",
  "difficulty": "Advanced",
  "date": "2026-06-13T18:35:46.221Z",
  "coverImg": "https://images.unsplash.com/photo-1585829365295-ab7cd400c167?w=500&q=80",
  "content": "Team IC Assets (bil): $17.5 73. HUB Retirement -                                                                                                                                                                                                                                                                                                                                                                                                                                                                                                                                                                                                                                                                                                                                    Morgan Stanley Oswald Financial UBS Private Wealth Principal: Eric Bailey Team IC Assets (bil): $3.8 Carlsbad 64. Oswald Financial Institutional Consulting Russell LaGreca, Allan House 98. Graystone Consulting, Tampa, Fla.                                                                                                                                                                                                                                                                                                                                                                                                                                                                                                                                                                                                                                                                                                                                                 81. Capitol Group Team IC Assets (bil): $4.9 Principals: James Meek, Captrust Team IC Assets (bil): $5.5                                                                                                                                                                                                                        Principal: F Russell Purdy 55. Captrust Team Bailey Team IC Assets (bil): $4.1 Brett Herbison, Mike Engel                                                                                                                                                                                                                                                                                                                                                                                                                                                                           Team IC Assets (bil): $13.9                                                                                                                                                                                                                       Baltimore Columbia, S.C.\n\nPrincipals: Bob Dow,                                                                                                                                                                                                                                                                                                                                                                                                                                                                                  Peter Ciovacco Bank of America Team IC Assets (bil): $14.5                                                                                                                                                                                                                                                                                                                                                                                                                                                                                                                                                                                                                                                                                                                                                                                                                                                                                                                                                                                    The J.K. Meek Group                                                                                                                                                                                                                           David Isaacson, Matt McLaughlin, Institutional Consulting Oak Brook, Ill."
}