{
  "id": "docs_practical_english_usage_pt217",
  "title": "practical english usage - Part 217",
  "source": "docs",
  "difficulty": "Beginner",
  "date": "2026-06-13T19:03:47.144Z",
  "coverImg": "https://images.unsplash.com/photo-1585829365295-ab7cd400c167?w=500&q=80",
  "content": "She doesn't like olives, and neither do I.\n\n’ I've forgotten the address.’ ’ So have I.' Ellipsis also happens after so, neither and nor (►  309). Note the word order.\n\ngrammar •  280  ellipsis: infinitives Stay as long as you like.\n\nCome when you want (to). I’ll do what I like.\n\nthese are used after certain conjunctions - for instance when, if, what, as.\n\nHowever, to is often dropped after want, and almost always after like, when not (     ... I didn’t want.) My parents encouraged me to study art, but I didn’ t want to.\n\n’ Are you interested in working abroad? ’ I’d like to. ’ (     ... I'd like.) choose.\n\nWe   cannot usually leave out to after would like/love/hate/prefer, want and 3 (would)      like,    want,      etc ’ Can you start the car? ’ I’ll try (to).’ It also happens after verbs which  can stand alone without a following infinitive.\n\nYou can’ t force him  to leave home if he’s not ready (to).\n\nHe’ll never leave home; he hasn’t got the courage (to).\n\nand adjectives.\n\nIn some cases the whole infinitive can be left out. This happens after nouns 2 ellipsis     of  whole     infinitive:      I'll try.\n\nYou’ve got more freckles than you used to have, (     ¥oube-got more freckles not She hasn’t been promoted yet, but she ought to be. (     .. .-but she eugkt-to?) not There are more flowers than there used to be. (     ... than thereusedto.) Be and have (used for possession) are not usually dropped.\n\nInformation StructureSection 25 grammar •  Section 26  Written Texts text: for example the language of spoken reports, political speeches or lectures.\n\nsome of what is said here naturally applies also to more formal types of spoken especially those which  affect text construction and comprehension. Note that This Section deals with some of the more important elements of formal writing, setting - academic English has its own characteristics.\n\nThis is especially the case for those who  plan to use English in a university formal written texts, the conventions of formal writing still have to be learnt.\n\nspeakers of English and language learners - who  need to be able to handle each has its own necessary grammatical characteristics. For people - both native Nonetheless, speech and writing are separate channels of communication and the gap still further.\n\ninformal written communication through electronic media is helping to narrow writing is far closer to speech in its structure and vocabulary, and the growth of led to increased respect for the language of ‘ ordinary people’ . Much   modern badly-structured ‘ poor relation’ . Since that time, growing democratisation has extremely elaborate, while informal speech was seen as a kind of low-level century. In those days formal writing enjoyed very high prestige and could be The  gap between speech and writing has narrowed a great deal since the 19th subjects most often consist of a single pronoun.\n\nround a head noun. Spoken noun phrases generally contain few modifiers; with determiners, adjectives, nouns and postmodifying structures all clustering average can be double this. Written noun phrases can become very complex, length of an English clause in speech is seven words; in formal writing the structures, with information-bearing elements more spaced out. The  average dense packaging of information, while speech favours more linear, chained Because of this, writing tends towards ‘ architectural’  structuring, with relatively cannot listen at one’ s own speed.\n\nmaterial: one can read as slowly as one likes, backtracking as necessary, but one structures. Equally, readers are far better able than listeners to decode complex working memory capacity in their ability to build up and keep track of elaborate a high level of complexity. Speakers, composing in real time, are limited by Writers can pause, reflect, recast and revise, producing if they wish material with spoken      and   written      language INTRODUCTION Section 26  Written Texts grammar •  Section 26  Written Texts 298  punctuation: quotation marks 289  correspondence: letters                297   punctuation: dash 288  academic writing                                  296   punctuation: comma 287   repetition                                              295 punctuation: semi-colon 286   paragraphs                                            294   punctuation: colon 285 reading complicated structures                   mark and exclamation mark 284   discourse markers in writing               293   punctuation: full stop, question and adverbials                                      292  headlines 283   linking with conjunctions                     291   abbreviated styles 282  pronouns and other proforms                     messages, etc 281   formality                                               289   correspondence: emails, text CONTENTS     OF THIS  SECTION x   The  truck weighs 3,5 tons. ►    296.11 x   Have you met our handsome, new, financial director? ►    296.9 x  a green red and gold carpet ►    296.9 x  No one knew, how  serious the situation would become. ►    296.6 trouble. ►    296.6 x  Many commentators declared, that the economy was in serious ►     296.4 x  The  mainly foreign, labourers formed a large part of the work force."
}