{
  "id": "Economist_The_Economist_UK_Edition_14_Feb_2026_pt66",
  "title": "The Economist UK Edition 14 Feb 2026 - Part 66",
  "source": "Economist",
  "difficulty": "Advanced",
  "date": "2026-06-13T18:46:15.682Z",
  "coverImg": "https://images.unsplash.com/photo-1585829365295-ab7cd400c167?w=500&q=80",
  "content": "coherent project or ideology to fall back                                                                                                                                                                                                                                                                                                                                                                                                                                                                                                                                                                                                                                                                     bour right, is suspected of preparing a                                                                                                                                                                                                                                                                                                                                                                                                                                                                                                                                                                                                                                                                                             fury. Twice in a week he has been heck- communications and 11 ministers. With no                                                                                                                                                                                                                                                                                                                                                                                                                                                                                                                                                                                                                                                                                                                                                                                                                                                                                                                                                                                                                                                                                                                                                                                                                                                                                                                                                                                                                                terview Andrew. The king is feeling the lost two chiefs of staff, four directors of                                                                                                                                                                                                                                                                                                                                                                                                                                                                                                                                                                                                                                                                                                                                                                                                                                                                                                                                                                                                                                                                                                                                                                                                                                                                                                                                                                                                                                     ister, waded in, urging police to in- Source: Betfair Exchange ing and erratic. In 19 months Sir Keir has                                                                                                                                                                                                                                                                                                                                                                                                                                                                                                                                                                                                                                                                                                                                                                                                                                                                                                                                                                                                                                                                                                                                                                                                                                                                                                                                                                                                                                    Gordon Brown, a former prime min- 2026 the prime minister’s team is both overbear-                                                                                                                                                                                                                                                                                                                                                                                                                                                                                                                                                                                                                                                                                                                                                                                                                                                                                                                                                                                                                                                                                                                                                                                                                                                                                                                                                                                                                                ed child sex offender. On February 11th January                                                                                                                                                                                                                                                                                                                     February MP                                           s and ministers privately complain that                                                                                                                                                                                                                                                                                                                                                                                                                                                                                                                                                                                                                                                                                                                                                                                                                                                                                                                                                                                                                                                                                                                                                                                                                                                                                                                                                                                      dealings with Jeffrey Epstein, a convict- 0 Ed MilibandEd MilibandEd Miliband functional operation in Downing Street.                                                                                                                                                                                                                                                                                                                                                                                                                                                                                                                                                                                                                                                                                                                                                                                                                                                                                                                                                                                                                                                                                                                                                                                                                                                                                                                                                                                                                                    before America’s Congress on his The problem is compounded by a dys-                                                                                                                                                                                                                                                                                                                                                                                                                                                                                                                                                                                                                                                                                                                                                                                                                                                                                                                                                                                                                                                                                                                                                                                                                                                                                                                                                                                     merly Prince Andrew, should testify 5 before (too often) being abandoned.                                                                                                                                                                                                                                                                                                                                                                                                                                                                                                                                                                                                                                                                                                                                                                                                                                                                                                                                                                                                                                                                                                                                                                                                                                                                                                                                                                                                                                          Andrew Mountbatten-Windsor, for- 10 Unpopular policies incur political damage                                                                                                                                                                                                                                                                                                                                                                                                                                                                                                                                                                                                                                                                                                                                                                                                                                                                                                                                                                                                                                                                                                                                                                                                                                                                                                                                                                                                                                                                                       prime minister, suggested that ject—have turned into a rebellious bunch.                                                                                                                                                                                                                                                                                                                                                                                                                                                                                                                                                                                                                                                                                                                                                                                                                                                                                                                                                                                                                                                                                                                                                                                                                                                                                                                                                                                                                                                                                            AST MONTH                                                                                                                                                                                     Sir Keir Starmer, the 15 L StreetingStreetingStreeting own                                                                     MP                                           s—never sold on a Starmerite pro- WesWesWes 20 date for difficult choices in office. Sir Keir’s from Andrew’s Epstein mess BurnhamBurnhamBurnham RaynerRaynerRayner vance means the government has no man- 25 AndyAndyAndy The palace tries to limit the fallout AngelaAngelaAngela Sir Keir took office. A lack of realism in ad- 30 boats; the numbers are higher than when Nigel Farage                                                                                                                                                                                                                                                           Kemi Badenoch of migrants crossing the channel in small minister, implied betting-market probability, % The party claimed it would stop the arrival Chance of becoming the next British prime Brotherly shove to rise to the highest levels since the 1940s."
}