{
  "id": "The_Spectator_The_Spectator_-_May_23,_2026_pt76",
  "title": "The Spectator - May 23, 2026 - Part 76",
  "source": "The Spectator",
  "difficulty": "Intermediate",
  "date": "2026-06-13T19:05:12.890Z",
  "coverImg": "https://images.unsplash.com/photo-1585829365295-ab7cd400c167?w=500&q=80",
  "content": "the overwhelming abundance of an art form,                                                                                                                                                                                                                                                                                                                                                                                                                                                                                                                                                                                                                                                                    Writers. Put on for the Festival of Britain, it to commit to the production line as soon tendency of many people, presented with                                                                                                                                                                                                                                                                                                                                                                                                                                                                                                                                                                                                                                                                    formed Unesco, of 100 Modern Books and population especially at risk, women had ‘Oh, there they are. In the tiny notes.’ The                                                                                                                                                                                                                                                                                                                                                                                                                                                                                                                                                                                                                                                                       mounted on a suggestion from the recently war much of the time, putting the male academic analysis of the Eroica symphony.                                                                                                                                                                                                                                                                                                                                                                                                                                                                                                                                                                                                                                                                                                                                                                        I have a catalogue of a 1951 exhibition, Since most ancient states were at being presented with a severe                                                                                                                                                                                                                                                                                                                                                                                                                                                                                    the true life of the novel quickly evaporates.\n\nyears to catch on.\n\nArnold Schoenberg asked, on                                                                                                                                                                                                                                                                                                                                                                                                                                                                                    a stern reduction to a list declaring Greatness, though it seems to have taken 2,500 be said to have invented women’s lib,                                                                                                                                                                                                                                                                                                                                                                                                                                                                                                                                                                                                                                                                                                                                                                                                                             here are all my favourite parts?’ explorer joyously unearthing, and more like interesting things is that Plato could ‘W have done for us, but one of the most on endlessly about what the ancients One could go PHILIP HENSHER Why lists of great novels are so grating Plato, the proto-feminist ancient                                                                                                                                                                                     and                                                                                                   modern Classic mistakes Philip Hensher AM_23 May 2026_The Spectator.indd   21Philip Hensher AM_23 May 2026_The Spectator.indd   21                                                                                                                                                                                                                                                                                                                                                                                                                                                                                                                                                                                                                                                                                                                                                                                                                                                                                                                                                                                                                                                                                                                                                                                                                                                                                                                                                                                                                                                                                                                                                                                                                                                                                                                                                                                                                                                                                           20/05/2026   09:5020/05/2026   09:50 |                                                                                                                                                                                                 | the spectator                                                                                                                                                                                                                                      23 may 2026                                                                                                                                                                                  www.spectator.com                                                                                                                                                                                                                                                                                                                                                                                                                                                                                                                                                                                                                                                                                                                                                                                                                                                                                                                                                                                                                                                                                                                                                                                                                                                                                                                                                                                                                                                                                                                                                                                                                                                                                                                                                                                                                                                                                                                                                    21 Gaskell, Margaret Oliphant. But Oliphant’s                                                                                                                                                                                                                                                                                                                                                                                                                                                                                                                                                                                                                                                                    examine a writing life in                                                                                                                                                                                                                                                                                                                                                            Pendennis, which,                                                                                                                                                                                                                                                                                                                         Britain is published by Pelican in September."
}